codemie_sdk/__init__.py
codemie_sdk/auth/__init__.py
codemie_sdk/auth/credentials.py
codemie_sdk/client/__init__.py
codemie_sdk/client/client.py
codemie_sdk/exceptions.py
codemie_sdk/models/assistant.py
codemie_sdk/models/common.py
codemie_sdk/models/datasource.py
codemie_sdk/models/integration.py
codemie_sdk/models/llm.py
codemie_sdk/models/task.py
codemie_sdk/models/user.py
codemie_sdk/models/workflow.py
codemie_sdk/services/assistant.py
codemie_sdk/services/datasource.py
codemie_sdk/services/integration.py
codemie_sdk/services/llm.py
codemie_sdk/services/task.py
codemie_sdk/services/user.py
codemie_sdk/services/workflow.py
codemie_sdk/services/workflow_execution.py
codemie_sdk/utils/__init__.py
codemie_sdk/utils/http.py
codemie_sdk_python_az-0.1000.6.dist-info/LICENSE
codemie_sdk_python_az-0.1000.6.dist-info/METADATA
codemie_sdk_python_az-0.1000.6.dist-info/WHEEL
codemie_sdk_python_az-0.1000.6.dist-info/RECORD
