Metadata-Version: 2.1
Name: codemie-sdk-python-az
Version: 0.1000.6
Summary: CodeMie SDK for Python
Author: Vadym Vlasenko
Author-email: vadym_vlasenko@epam.com
Requires-Python: >=3.12,<4.0
Classifier: Programming Language :: Python :: 3
Classifier: Programming Language :: Python :: 3.12
Requires-Dist: pydantic (>=2.6.1,<3.0.0)
Requires-Dist: pytest-cov (>=6.0.0,<7.0.0)
Requires-Dist: requests (>=2.31.0,<3.0.0)
Requires-Dist: ruff (>=0.11.0,<0.12.0)
